konstantin_docs/__init__.py
konstantin_docs/dia/__init__.py
konstantin_docs/dia/base.py
konstantin_docs/dia/c4/__init__.py
konstantin_docs/dia/c4/base.py
konstantin_docs/dia/c4/c4.py
konstantin_docs/dia/c4/component.py
konstantin_docs/dia/c4/container.py
konstantin_docs/dia/c4/context.py
konstantin_docs/dia/c4/rel.py
konstantin_docs/dia/c4/sprite.py
konstantin_docs/dia/c4/sprite_lib/__init__.py
konstantin_docs/dia/c4/sprite_lib/tupadr3.py
konstantin_docs/dia/c4/sprite_lib/tupadr3_lib/__init__.py
konstantin_docs/dia/c4/sprite_lib/tupadr3_lib/devicons.py
konstantin_docs/dia/c4/sprite_lib/tupadr3_lib/devicons2.py
konstantin_docs/dia/c4/sprite_lib/tupadr3_lib/font_awesome_5.py
konstantin_docs/dia/c4/tag.py
konstantin_docs/dia/mermaid_er/__init__.py
konstantin_docs/dia/mermaid_er/main.py
konstantin_docs/dia/mermaid_state/mermaid_state.py
konstantin_docs/dia/nwdiag.py
konstantin_docs/main.py
konstantin_docs/service/__init__.py
konstantin_docs/service/kroki.py
konstantin_docs-0.0.14.dist-info/WHEEL
konstantin_docs-0.0.14.dist-info/METADATA
konstantin_docs-0.0.14.dist-info/RECORD
