Metadata-Version: 2.1
Name: konstantin-docs
Version: 0.0.14
Summary: Генерация документации
Home-page: https://github.com/Konstantin-Dudersky/konstantin_docs
Author: Konstantin-Dudersky
Author-email: Konstantin.Dudersky@gmail.com
Requires-Python: >=3.10,<4.0
Classifier: Programming Language :: Python :: 3
Classifier: Programming Language :: Python :: 3.10
Requires-Dist: requests
Requires-Dist: typing_extensions
Project-URL: Repository, https://github.com/Konstantin-Dudersky/konstantin_docs
